storages_folder
