Metadata-Version: 1.1
Name: django-storages-folder
Version: 0.1.3
Summary: django-storages-redux extension to allow separate folders for media and static files
Home-page: https://github.com/RyanPineo/django-storages-folder
Author: Ryan Pineo
Author-email: ryanpineo@gmail.com
License: BSD
Platform: UNKNOWN
Classifier: Framework :: Django
Classifier: Programming Language :: Python
Classifier: Programming Language :: Python :: 2
Classifier: Programming Language :: Python :: 3
